pardakht/__init__.py
pardakht/dargah.py
pardakht-0.2.0.dist-info/METADATA
pardakht-0.2.0.dist-info/WHEEL
pardakht-0.2.0.dist-info/top_level.txt
pardakht-0.2.0.dist-info/RECORD
