Metadata-Version: 2.4
Name: pardakht
Version: 0.2.0
Summary: A simple Python package to integrate bots or apps with payment gateways like ZarinPal.
Author-email: Ali Heydari <imrrobat@gmail.com>
License: MIT
Requires-Python: >=3.7
Requires-Dist: requests>=2.0.0
